{
    "Data": [
        {
            "Name": "THROAT SURGERY",
            "GameUrl": "https://html5.gamedistribution.com/31e48cae98cc476d83ae201988d5469e/",
            "GameIconUrl": "https://img.gamedistribution.com/31e48cae98cc476d83ae201988d5469e-512x512.jpeg",
            "Icon": {
                "instanceID": 0
            },
            "Stars": 3,
            "IsBEST": true,
            "IsNew": false,
            "IsVip": false
        },
        {
            "Name": "SLINGSHOT JETPACK",
            "GameUrl": "https://html5.gamedistribution.com/0851014c5d0f4dc8918e89ca6128f1e8/",
            "GameIconUrl": "https://img.gamedistribution.com/0851014c5d0f4dc8918e89ca6128f1e8-512x512.jpeg",
            "Icon": {
                "instanceID": 0
            },
            "Stars": 4,
            "IsBEST": true,
            "IsNew": true,
            "IsVip": true
        },{
            "Name": "REALISTIC PARKING",
            "GameUrl": "https://html5.gamedistribution.com/0020f02a8a9149af85fa448c788e683b/",
            "GameIconUrl": "https://img.gamedistribution.com/0020f02a8a9149af85fa448c788e683b-512x512.jpeg",
            "Icon": {
                "instanceID": 0
            },
            "Stars": 3,
            "IsBEST": true,
            "IsNew": true,
            "IsVip": true
        },{
            "Name": "OBJECT HUNT",
            "GameUrl": "https://html5.gamedistribution.com/97203c38c749435382991c18cd1d891a/",
            "GameIconUrl": "https://img.gamedistribution.com/97203c38c749435382991c18cd1d891a-512x512.jpeg",
            "Icon": {
                "instanceID": 0
            },
            "Stars": 3,
            "IsBEST": true,
            "IsNew": false,
            "IsVip": false
        },{
            "Name": "GALACTIC WAR",
            "GameUrl": "https://html5.gamedistribution.com/14272ee6676940649077fa92b7896d50/",
            "GameIconUrl": "https://img.gamedistribution.com/14272ee6676940649077fa92b7896d50-512x512.jpeg",
            "Icon": {
                "instanceID": 0
            },
            "Stars": 3,
            "IsBEST": true,
            "IsNew": false,
            "IsVip": false
        },{
            "Name": "PAPER AIRPLANE",
            "GameUrl": "https://html5.gamedistribution.com/ebe67c95be0b42589ec62e0e5bee6127/",
            "GameIconUrl": "https://img.gamedistribution.com/ebe67c95be0b42589ec62e0e5bee6127-512x512.jpeg",
            "Icon": {
                "instanceID": 0
            },
            "Stars": 3,
            "IsBEST": true,
            "IsNew": false,
            "IsVip": false
        },{
            "Name": "MERGE AND FLY",
            "GameUrl": "https://html5.gamedistribution.com/263986930e564c4e9a6c19c9302d6090/",
            "GameIconUrl": "https://img.gamedistribution.com/263986930e564c4e9a6c19c9302d6090-512x512.jpeg",
            "Icon": {
                "instanceID": 0
            },
            "Stars": 3,
            "IsBEST": true,
            "IsNew": false,
            "IsVip": false
        },{
            "Name": "DIRT BIKE RALLY",
            "GameUrl": "https://html5.gamedistribution.com/7fbe01f54d884e27881e61bc500a6c6d/",
            "GameIconUrl": "https://img.gamedistribution.com/7fbe01f54d884e27881e61bc500a6c6d-512x512.jpeg",
            "Icon": {
                "instanceID": 0
            },
            "Stars": 3,
            "IsBEST": true,
            "IsNew": false,
            "IsVip": false
        },{
            "Name": "PET SHOP",
            "GameUrl": "https://html5.gamedistribution.com/0d48c9cf1b634646b414a519049f51b7/",
            "GameIconUrl": "https://img.gamedistribution.com/0d48c9cf1b634646b414a519049f51b7-512x384.jpeg",
            "Icon": {
                "instanceID": 0
            },
            "Stars": 4,
            "IsBEST": true,
            "IsNew": false,
            "IsVip": true
        },{
            "Name": "SCHOOL BUS",
            "GameUrl": "https://html5.gamedistribution.com/6635799588e24629b3d3fdb80972061a/",
            "GameIconUrl": "https://img.gamedistribution.com/6635799588e24629b3d3fdb80972061a-512x384.jpeg",
            "Icon": {
                "instanceID": 0
            },
            "Stars": 3,
            "IsBEST": true,
            "IsNew": false,
            "IsVip": true
        },{
            "Name": "PAPER FLICK",
            "GameUrl": "https://html5.gamedistribution.com/dd1fc7237d4a44d497b793ee78db423d/",
            "GameIconUrl": "https://img.gamedistribution.com/dd1fc7237d4a44d497b793ee78db423d-512x512.jpeg",
            "Icon": {
                "instanceID": 0
            },
            "Stars": 4,
            "IsBEST": true,
            "IsNew": false,
            "IsVip": true
        },{
            "Name": "DENTAL CARE GAME",
            "GameUrl": "https://html5.gamedistribution.com/bac933bb80014eca8b5ec99b0f3e0d3e/",
            "GameIconUrl": "https://img.gamedistribution.com/bac933bb80014eca8b5ec99b0f3e0d3e-512x384.jpeg",
            "Icon": {
                "instanceID": 0
            },
            "Stars": 4,
            "IsBEST": true,
            "IsNew": true,
            "IsVip": true
        },{
            "Name": "IDLE AIRLINE TYCOON",
            "GameUrl": "https://html5.gamedistribution.com/6095edb29feb47a1af1a9d295eb58f5b/",
            "GameIconUrl": "https://img.gamedistribution.com/6095edb29feb47a1af1a9d295eb58f5b-512x512.jpeg",
            "Icon": {
                "instanceID": 0
            },
            "Stars": 2,
            "IsBEST": true,
            "IsNew": false,
            "IsVip": false
        },{
            "Name": "ACE MOTO RIDER",
            "GameUrl": "https://html5.gamedistribution.com/ee519682d930415a82e9665e4d98d243/",
            "GameIconUrl": "https://img.gamedistribution.com/ee519682d930415a82e9665e4d98d243-512x384.jpeg",
            "Icon": {
                "instanceID": 0
            },
            "Stars": 3,
            "IsBEST": true,
            "IsNew": true,
            "IsVip": true
        },{
            "Name": "BABY TAYLOR",
            "GameUrl": "https://html5.gamedistribution.com/7549532a2d7444ea82462d4bc0730cfb/",
            "GameIconUrl": "https://img.gamedistribution.com/7549532a2d7444ea82462d4bc0730cfb-512x384.jpeg",
            "Icon": {
                "instanceID": 0
            },
            "Stars": 3,
            "IsBEST": true,
            "IsNew": false,
            "IsVip": false
        },
        {
            "Name": "KIDS MOVIE",
            "GameUrl": "https://html5.gamedistribution.com/f830e5aa15324461b4dc3e1e5fc07c91/",
            "GameIconUrl": "https://img.gamedistribution.com/f830e5aa15324461b4dc3e1e5fc07c91-512x384.jpeg",
            "Icon": {
                "instanceID": 0
            },
            "Stars": 3,
            "IsBEST": true,
            "IsNew": false,
            "IsVip": false
        },{
            "Name": "PING PONG",
            "GameUrl": "https://html5.gamedistribution.com/dcf28170ec5940f2b0e3f4a12ac179c9/",
            "GameIconUrl": "https://img.gamedistribution.com/dcf28170ec5940f2b0e3f4a12ac179c9-512x512.jpeg",
            "Icon": {
                "instanceID": 0
            },
            "Stars": 3,
            "IsBEST": true,
            "IsNew": false,
            "IsVip": false
        },{
            "Name": "FUNNY EYE SURGERY",
            "GameUrl": "https://html5.gamedistribution.com/1bbe6eea43ca4bafb300e8bffd6e6d21/",
            "GameIconUrl": "https://img.gamedistribution.com/1bbe6eea43ca4bafb300e8bffd6e6d21-512x512.jpeg",
            "Icon": {
                "instanceID": 0
            },
            "Stars": 3,
            "IsBEST": true,
            "IsNew": false,
            "IsVip": true
        },{
            "Name": "BABY CARE",
            "GameUrl": "https://html5.gamedistribution.com/0956e98188e2457aa471182f871c4696/",
            "GameIconUrl": "https://img.gamedistribution.com/0956e98188e2457aa471182f871c4696-512x384.jpeg",
            "Icon": {
                "instanceID": 0
            },
            "Stars": 3,
            "IsBEST": true,
            "IsNew": false,
            "IsVip": false
        },{
            "Name": "HAIR SALON",
            "GameUrl": "https://html5.gamedistribution.com/ce8a0bdacb3e4f92a58f417dcd552030/",
            "GameIconUrl": "https://img.gamedistribution.com/ce8a0bdacb3e4f92a58f417dcd552030-512x512.jpeg",
            "Icon": {
                "instanceID": 0
            },
            "Stars": 4,
            "IsBEST": true,
            "IsNew": true,
            "IsVip": true
        },{
            "Name": "REPAIR SHOP",
            "GameUrl": "https://html5.gamedistribution.com/f38c156b76c740c48dea1b01c00abf4a/",
            "GameIconUrl": "https://img.gamedistribution.com/f38c156b76c740c48dea1b01c00abf4a-512x384.jpeg",
            "Icon": {
                "instanceID": 0
            },
            "Stars": 3,
            "IsBEST": true,
            "IsNew": false,
            "IsVip": true
        },{
            "Name": "NAIL DOCTOR",
            "GameUrl": "https://html5.gamedistribution.com/80d1021fafef4b8bb95c571a9925eb29/",
            "GameIconUrl": "https://img.gamedistribution.com/80d1021fafef4b8bb95c571a9925eb29-512x384.jpeg",
            "Icon": {
                "instanceID": 0
            },
            "Stars": 3,
            "IsBEST": true,
            "IsNew": false,
            "IsVip": false
        },{
            "Name": "RESCUE GARDENER",
            "GameUrl": "https://html5.gamedistribution.com/5c69fd5cb1ab4fbeaf4957ea6620d569/",
            "GameIconUrl": "https://img.gamedistribution.com/5c69fd5cb1ab4fbeaf4957ea6620d569-512x512.jpeg",
            "Icon": {
                "instanceID": 0
            },
            "Stars": 3,
            "IsBEST": true,
            "IsNew": false,
            "IsVip": true
        },{
            "Name": "SODA CAN",
            "GameUrl": "https://html5.gamedistribution.com/a3a506c515584d31b2bd6f6bf78cae81/",
            "GameIconUrl": "https://img.gamedistribution.com/a3a506c515584d31b2bd6f6bf78cae81-512x512.jpeg",
            "Icon": {
                "instanceID": 0
            },
            "Stars": 4,
            "IsBEST": true,
            "IsNew": false,
            "IsVip": true
        },{
            "Name": "KING OF STRINGS",
            "GameUrl": "https://html5.gamedistribution.com/3f314f752d924e388e5a47d3badc7bed/",
            "GameIconUrl": "https://img.gamedistribution.com/3f314f752d924e388e5a47d3badc7bed-512x512.jpeg",
            "Icon": {
                "instanceID": 0
            },
            "Stars": 3,
            "IsBEST": true,
            "IsNew": false,
            "IsVip": false
        },{
            "Name": "AXE MASTER",
            "GameUrl": "https://html5.gamedistribution.com/62d0de42d6c448a3a2b89c4054daa4c7/",
            "GameIconUrl": "https://img.gamedistribution.com/62d0de42d6c448a3a2b89c4054daa4c7-512x512.jpeg",
            "Icon": {
                "instanceID": 0
            },
            "Stars": 3,
            "IsBEST": true,
            "IsNew": false,
            "IsVip": false
        },{
            "Name": "RESCUE CARPENTER",
            "GameUrl": "https://html5.gamedistribution.com/c2fea32d218345a482d9d3af3b6e916e/",
            "GameIconUrl": "https://img.gamedistribution.com/c2fea32d218345a482d9d3af3b6e916e-512x512.jpeg",
            "Icon": {
                "instanceID": 0
            },
            "Stars": 3,
            "IsBEST": true,
            "IsNew": false,
            "IsVip": false
        },{
            "Name": "ARCADE BUILDER",
            "GameUrl": "https://html5.gamedistribution.com/1a39e39e04bc471aadd76cda27bb46cd/",
            "GameIconUrl": "https://img.gamedistribution.com/1a39e39e04bc471aadd76cda27bb46cd-512x512.jpeg",
            "Icon": {
                "instanceID": 0
            },
            "Stars": 3,
            "IsBEST": true,
            "IsNew": false,
            "IsVip": false
        },{
            "Name": "BLENDY JUICY",
            "GameUrl": "https://html5.gamedistribution.com/00f8570d8de24025b387e09496084480/",
            "GameIconUrl": "https://img.gamedistribution.com/00f8570d8de24025b387e09496084480-512x384.jpeg",
            "Icon": {
                "instanceID": 0
            },
            "Stars": 4,
            "IsBEST": true,
            "IsNew": true,
            "IsVip": true
        },{
            "Name": "CLIMB THE ROCKS",
            "GameUrl": "https://html5.gamedistribution.com/2af98c25d77f4027a3113875fab13f4e/",
            "GameIconUrl": "https://img.gamedistribution.com/2af98c25d77f4027a3113875fab13f4e-512x512.jpeg",
            "Icon": {
                "instanceID": 0
            },
            "Stars": 4,
            "IsBEST": true,
            "IsNew": false,
            "IsVip": true
        },{
            "Name": "NEW HOUSE",
            "GameUrl": "https://html5.gamedistribution.com/5193a99384e242ae81b6b9aee31ca3a8/",
            "GameIconUrl": "https://img.gamedistribution.com/5193a99384e242ae81b6b9aee31ca3a8-512x384.jpeg",
            "Icon": {
                "instanceID": 0
            },
            "Stars": 3,
            "IsBEST": true,
            "IsNew": false,
            "IsVip": false
        },{
            "Name": "BABY CARE",
            "GameUrl": "https://html5.gamedistribution.com/75051fe589a34cd8a68d72993a2c6a70/",
            "GameIconUrl": "https://img.gamedistribution.com/75051fe589a34cd8a68d72993a2c6a70-512x384.jpeg",
            "Icon": {
                "instanceID": 0
            },
            "Stars": 3,
            "IsBEST": true,
            "IsNew": false,
            "IsVip": false
        },{
            "Name": "EYE DOCTOR",
            "GameUrl": "https://html5.gamedistribution.com/2a1a0e1eae54485288bc515f8d6e4dee/",
            "GameIconUrl": "https://img.gamedistribution.com/2a1a0e1eae54485288bc515f8d6e4dee-512x384.jpeg",
            "Icon": {
                "instanceID": 0
            },
            "Stars": 3,
            "IsBEST": true,
            "IsNew": false,
            "IsVip": false
        },{
            "Name": "911 AMBULANCE",
            "GameUrl": "https://html5.gamedistribution.com/138239ec3bdd47bfa469b00243867319/",
            "GameIconUrl": "https://img.gamedistribution.com/138239ec3bdd47bfa469b00243867319-512x384.jpeg",
            "Icon": {
                "instanceID": 0
            },
            "Stars": 3,
            "IsBEST": true,
            "IsNew": false,
            "IsVip": true
        },{
            "Name": "NOSE SURGERY",
            "GameUrl": "https://html5.gamedistribution.com/a185069d961b4ec5acdab70c1848ceee/",
            "GameIconUrl": "https://img.gamedistribution.com/a185069d961b4ec5acdab70c1848ceee-512x512.jpeg",
            "Icon": {
                "instanceID": 0
            },
            "Stars": 3,
            "IsBEST": true,
            "IsNew": false,
            "IsVip": true
        },{
            "Name": "SNOWBOARD HERO",
            "GameUrl": "https://html5.gamedistribution.com/716194ae04b34da6830eff3043d2af87/",
            "GameIconUrl": "https://img.gamedistribution.com/716194ae04b34da6830eff3043d2af87-512x512.jpeg",
            "Icon": {
                "instanceID": 0
            },
            "Stars": 3,
            "IsBEST": true,
            "IsNew": false,
            "IsVip": true
        },
        {
            "Name": "BITCOIN MINE",
            "GameUrl": "https://html5.gamedistribution.com/08b3434b0b354f3cbc6b40922ce44287/",
            "GameIconUrl": "https://img.gamedistribution.com/08b3434b0b354f3cbc6b40922ce44287-512x512.jpeg",
            "Icon": {
                "instanceID": 0
            },
            "Stars": 3,
            "IsBEST": true,
            "IsNew": false,
            "IsVip": true
        },{
            "Name": "HOP STARS",
            "GameUrl": "https://html5.gamedistribution.com/426489ae6c5049edbbd4a696ed8aaf3e/",
            "GameIconUrl": "https://img.gamedistribution.com/426489ae6c5049edbbd4a696ed8aaf3e-512x512.jpeg",
            "Icon": {
                "instanceID": 0
            },
            "Stars": 3,
            "IsBEST": true,
            "IsNew": false,
            "IsVip": true
        },{
            "Name": "GOLD SEEKER",
            "GameUrl": "https://html5.gamedistribution.com/7dd3e32934c84068b67d5ab594ef9035/",
            "GameIconUrl": "https://img.gamedistribution.com/7dd3e32934c84068b67d5ab594ef9035-512x384.jpeg",
            "Icon": {
                "instanceID": 0
            },
            "Stars": 3,
            "IsBEST": true,
            "IsNew": false,
            "IsVip": false
        },{
            "Name": "ANIMAL DENTIST",
            "GameUrl": "https://html5.gamedistribution.com/987f4258b26c4d5fae790bd254004091/",
            "GameIconUrl": "https://img.gamedistribution.com/987f4258b26c4d5fae790bd254004091-512x512.jpeg",
            "Icon": {
                "instanceID": 0
            },
            "Stars": 3,
            "IsBEST": true,
            "IsNew": false,
            "IsVip": false
        },{
            "Name": "PIXEL WAR",
            "GameUrl": "https://html5.gamedistribution.com/65111637d9404ac79231a3a8789fba54/",
            "GameIconUrl": "https://img.gamedistribution.com/65111637d9404ac79231a3a8789fba54-512x512.jpeg",
            "Icon": {
                "instanceID": 0
            },
            "Stars": 3,
            "IsBEST": true,
            "IsNew": false,
            "IsVip": false
        },{
            "Name": "SKI HERO",
            "GameUrl": "https://html5.gamedistribution.com/ccc904bb601c4fe2ac637b47db6bba3c/",
            "GameIconUrl": "https://img.gamedistribution.com/ccc904bb601c4fe2ac637b47db6bba3c-512x512.jpeg",
            "Icon": {
                "instanceID": 0
            },
            "Stars": 4,
            "IsBEST": true,
            "IsNew": true,
            "IsVip": true
        },{
            "Name": "MINI GOLF",
            "GameUrl": "https://html5.gamedistribution.com/bb58de9c3c454866ae701458b2a6a570/",
            "GameIconUrl": "https://img.gamedistribution.com/bb58de9c3c454866ae701458b2a6a570-512x512.jpeg",
            "Icon": {
                "instanceID": 0
            },
            "Stars": 3,
            "IsBEST": true,
            "IsNew": false,
            "IsVip": false
        },{
            "Name": "FOODY AVENUE",
            "GameUrl": "http://html5.gamedistribution.com/5c8c85271a31480f8967e92755cc2788/",
            "GameIconUrl": "https://img.gamedistribution.com/5c8c85271a31480f8967e92755cc2788.jpg",
            "Icon": {
                "instanceID": 0
            },
            "Stars": 3,
            "IsBEST": true,
            "IsNew": false,
            "IsVip": false
        },{
            "Name": "ICE QUEEN",
            "GameUrl": "https://html5.gamedistribution.com/96604ff9c9924426827697577a23dcac/",
            "GameIconUrl": "https://img.gamedistribution.com/96604ff9c9924426827697577a23dcac.jpg",
            "Icon": {
                "instanceID": 0
            },
            "Stars": 4,
            "IsBEST": true,
            "IsNew": false,
            "IsVip": true
        },{
            "Name": "VLOGGERS LIFE",
            "GameUrl": "http://html5.gamedistribution.com/e77929d457ef490ba31fb22d93997cf2/",
            "GameIconUrl": "https://img.gamedistribution.com/e77929d457ef490ba31fb22d93997cf2.jpg",
            "Icon": {
                "instanceID": 0
            },
            "Stars": 3,
            "IsBEST": true,
            "IsNew": false,
            "IsVip": false
        },{
            "Name": "HAPPY DESSERT",
            "GameUrl": "http://html5.gamedistribution.com/e1d09f3312c84aa0ad8855b1be201cb6/",
            "GameIconUrl": "https://img.gamedistribution.com/e1d09f3312c84aa0ad8855b1be201cb6.jpg",
            "Icon": {
                "instanceID": 0
            },
            "Stars": 3,
            "IsBEST": true,
            "IsNew": false,
            "IsVip": false
        },{
            "Name": "TALKING PIG MIMY",
            "GameUrl": "http://html5.gamedistribution.com/16956bb86cd4490baccd99a04a7955be/",
            "GameIconUrl": "https://img.gamedistribution.com/16956bb86cd4490baccd99a04a7955be.jpg",
            "Icon": {
                "instanceID": 0
            },
            "Stars": 2,
            "IsBEST": true,
            "IsNew": false,
            "IsVip": false
        },{
            "Name": "MOMMY BIRTH",
            "GameUrl": "https://html5.gamedistribution.com/a54d0329c0704f83a778077a949c50ed/",
            "GameIconUrl": "https://img.gamedistribution.com/a54d0329c0704f83a778077a949c50ed.jpg",
            "Icon": {
                "instanceID": 0
            },
            "Stars": 3,
            "IsBEST": true,
            "IsNew": false,
            "IsVip": false
        }
    ]
}